{
  "tableData": [
    {
      "id": 1,
      "audienceName": "Audoemce Name",
      "member": "9943",
      "dateOfCreate": "24/11/1983"
    },
    {
      "id": 2,
      "audienceName": "Audoemce Name",
      "member": "9943",
      "dateOfCreate": "24/11/1983"
    },
    {
      "id": 3,
      "audienceName": "Audoemce Name",
      "member": "9943",
      "dateOfCreate": "24/11/1983"
    },
    {
      "id": 4,
      "audienceName": "Audoemce Name",
      "member": "9943",
      "dateOfCreate": "24/11/1983"
    },
    {
      "id": 5,
      "audienceName": "Audoemce Name",
      "member": "9943",
      "dateOfCreate": "24/11/1983"
    }
  ]
}
